{
   "variables": {
      "COLOR_CANVAS": "#00000000", 
      "COLOR_ARROW": "#000000FF", 
      "COLOR_LINE_SINGLE_SUB": "#0000FF80", 
      "COLOR_BACKGROUND": "#00000000", 
      "LINE_WIDTH_PRIMARY": "3", 
      "COLOR_LINE_SINGLE": "#0000FFFF", 
      "COLOR_AXIS": "#000000FF", 
      "LINE_WIDTH_SECONDARY": "1", 
      "COLOR_FONT": "#000000FF"
   }, 
   "page": {
      "plots": [
         {
            "type": "CPU/overview", 
            "subplots": {
               "plots": [
                  {
                     "type": "CPU/overview"
                  }, 
                  {
                     "type": "CPU/idle"
                  }, 
                  {
                     "type": "CPU/nice"
                  }, 
                  {
                     "type": "CPU/user"
                  }, 
                  {
                     "type": "CPU/system"
                  }, 
                  {
                     "type": "CPU/wait"
                  }, 
                  {
                     "type": "CPU/steal"
                  }, 
                  {
                     "type": "CPU/softirq"
                  }, 
                  {
                     "type": "CPU/interrupt"
                  }
               ], 
               "title": "CPU details"
            }
         }, 
         {
            "type": "Battery/voltage", 
            "subplots": {
               "plots": [
                  {
                     "type": "Battery/voltage"
                  }, 
                  {
                     "type": "Battery/current"
                  }
               ], 
               "title": "Battery details"
            }
         }, 
         {
            "type": "Storage/root", 
            "subplots": {
               "plots": [
                  {
                     "type": "Storage/root"
                  }
               ], 
               "title": "Storage details"
            }
         }, 
         {
            "type": "Memory/overview", 
            "subplots": {
               "plots": [
                  {
                     "type": "Memory/overview"
                  }, 
                  {
                     "type": "Memory/free"
                  }, 
                  {
                     "type": "Memory/cached"
                  }, 
                  {
                     "type": "Memory/buffered"
                  }, 
                  {
                     "type": "Memory/used"
                  }, 
                  {
                     "type": "Memory/slab_recl"
                  }, 
                  {
                     "type": "Memory/slab_unrecl"
                  }
               ], 
               "title": "Memory details"
            }
         }, 
         {
            "type": "Load/load"
         }, 
         {
            "type": "Context/context_switch", 
            "subplots": {
               "plots": [
                  {
                     "type": "Context/context_switch"
                  }, 
                  {
                     "type": "Entropy/entropy"
                  }, 
                  {
                     "type": "Uptime/uptime"
                  }
               ], 
               "title": "Misc details"
            }
         }
      ], 
      "title": "Overview"
   }, 
   "types": {
      "CPU/system": {
         "files": [
            "cpu/percent-system.rrd"
         ], 
         "command": "-t \"CPU system, %\" --upper-limit 100 --lower-limit 0 --rigid --color BACK$COLOR_BACKGROUND$ --color SHADEA$COLOR_BACKGROUND$ --color SHADEB$COLOR_BACKGROUND$ --color CANVAS$COLOR_CANVAS$  --color FONT$COLOR_FONT$ --color AXIS$COLOR_AXIS$ --color ARROW$COLOR_ARROW$ DEF:system=cpu/percent-system.rrd:value:AVERAGE DEF:system_min=cpu/percent-system.rrd:value:MIN DEF:system_max=cpu/percent-system.rrd:value:MAX CDEF:system_max_min_delta=system_max,system_min,- LINE:system_min AREA:system_max_min_delta$COLOR_LINE_SINGLE_SUB$::STACK LINE$LINE_WIDTH_PRIMARY$:system$COLOR_LINE_SINGLE$:\"system\\l\" COMMENT:\\u GPRINT:system:AVERAGE:\"Avr %1.0lf\" GPRINT:system_min:MIN:\"Min %1.0lf\" GPRINT:system_max:MAX:\"Max %1.0lf\" GPRINT:system:LAST:\"Last %1.0lf\\r\"  "
      }, 
      "CPU/overview": {
         "files": [
            "cpu/percent-interrupt.rrd", 
            "cpu/percent-softirq.rrd", 
            "cpu/percent-steal.rrd", 
            "cpu/percent-wait.rrd", 
            "cpu/percent-system.rrd", 
            "cpu/percent-user.rrd", 
            "cpu/percent-nice.rrd", 
            "cpu/percent-idle.rrd"
         ], 
         "command": "-t \"CPU usage, %\" --upper-limit 100 --lower-limit 0 --rigid --color BACK$COLOR_BACKGROUND$ --color SHADEA$COLOR_BACKGROUND$ --color SHADEB$COLOR_BACKGROUND$ --color CANVAS$COLOR_CANVAS$  --color FONT$COLOR_FONT$ --color AXIS$COLOR_AXIS$ --color ARROW$COLOR_ARROW$ DEF:interrupt=cpu/percent-interrupt.rrd:value:AVERAGE DEF:softirq=cpu/percent-softirq.rrd:value:AVERAGE DEF:steal=cpu/percent-steal.rrd:value:AVERAGE DEF:wait=cpu/percent-wait.rrd:value:AVERAGE DEF:system=cpu/percent-system.rrd:value:AVERAGE DEF:user=cpu/percent-user.rrd:value:AVERAGE DEF:nice=cpu/percent-nice.rrd:value:AVERAGE DEF:idle=cpu/percent-idle.rrd:value:AVERAGE AREA:interrupt#E41A1CFF:\"interrupt\\l\" COMMENT:\\u GPRINT:interrupt:AVERAGE:\"Avr %2.0lf\" GPRINT:interrupt:MIN:\"Min %2.0lf\" GPRINT:interrupt:MAX:\"Max %2.0lf\" GPRINT:interrupt:LAST:\"Last %2.0lf\\r\"  AREA:softirq#377EB8FF:\"softirq\\l\":STACK COMMENT:\\u GPRINT:softirq:AVERAGE:\"Avr %2.0lf\" GPRINT:softirq:MIN:\"Min %2.0lf\" GPRINT:softirq:MAX:\"Max %2.0lf\" GPRINT:softirq:LAST:\"Last %2.0lf\\r\"  AREA:steal#4DAF4AFF:\"steal\\l\":STACK COMMENT:\\u GPRINT:steal:AVERAGE:\"Avr %2.0lf\" GPRINT:steal:MIN:\"Min %2.0lf\" GPRINT:steal:MAX:\"Max %2.0lf\" GPRINT:steal:LAST:\"Last %2.0lf\\r\"  AREA:wait#984EA3FF:\"wait\\l\":STACK COMMENT:\\u GPRINT:wait:AVERAGE:\"Avr %2.0lf\" GPRINT:wait:MIN:\"Min %2.0lf\" GPRINT:wait:MAX:\"Max %2.0lf\" GPRINT:wait:LAST:\"Last %2.0lf\\r\"  AREA:system#FF7F00FF:\"system\\l\":STACK COMMENT:\\u GPRINT:system:AVERAGE:\"Avr %2.0lf\" GPRINT:system:MIN:\"Min %2.0lf\" GPRINT:system:MAX:\"Max %2.0lf\" GPRINT:system:LAST:\"Last %2.0lf\\r\"  AREA:user#FFFF33FF:\"user\\l\":STACK COMMENT:\\u GPRINT:user:AVERAGE:\"Avr %2.0lf\" GPRINT:user:MIN:\"Min %2.0lf\" GPRINT:user:MAX:\"Max %2.0lf\" GPRINT:user:LAST:\"Last %2.0lf\\r\"  AREA:nice#A65628FF:\"nice\\l\":STACK COMMENT:\\u GPRINT:nice:AVERAGE:\"Avr %2.0lf\" GPRINT:nice:MIN:\"Min %2.0lf\" GPRINT:nice:MAX:\"Max %2.0lf\" GPRINT:nice:LAST:\"Last %2.0lf\\r\"  AREA:idle#00000000:\"idle\\l\":STACK COMMENT:\\u GPRINT:idle:AVERAGE:\"Avr %2.0lf\" GPRINT:idle:MIN:\"Min %2.0lf\" GPRINT:idle:MAX:\"Max %2.0lf\" GPRINT:idle:LAST:\"Last %2.0lf\\r\"  "
      }, 
      "CPU/nice": {
         "files": [
            "cpu/percent-nice.rrd"
         ], 
         "command": "-t \"CPU nice, %\" --upper-limit 100 --lower-limit 0 --rigid --color BACK$COLOR_BACKGROUND$ --color SHADEA$COLOR_BACKGROUND$ --color SHADEB$COLOR_BACKGROUND$ --color CANVAS$COLOR_CANVAS$  --color FONT$COLOR_FONT$ --color AXIS$COLOR_AXIS$ --color ARROW$COLOR_ARROW$ DEF:nice=cpu/percent-nice.rrd:value:AVERAGE DEF:nice_min=cpu/percent-nice.rrd:value:MIN DEF:nice_max=cpu/percent-nice.rrd:value:MAX CDEF:nice_max_min_delta=nice_max,nice_min,- LINE:nice_min AREA:nice_max_min_delta$COLOR_LINE_SINGLE_SUB$::STACK LINE$LINE_WIDTH_PRIMARY$:nice$COLOR_LINE_SINGLE$:\"nice\\l\" COMMENT:\\u GPRINT:nice:AVERAGE:\"Avr %1.0lf\" GPRINT:nice_min:MIN:\"Min %1.0lf\" GPRINT:nice_max:MAX:\"Max %1.0lf\" GPRINT:nice:LAST:\"Last %1.0lf\\r\"  "
      }, 
      "CPU/idle": {
         "files": [
            "cpu/percent-idle.rrd"
         ], 
         "command": "-t \"CPU idle, %\" --upper-limit 100 --lower-limit 0 --rigid --color BACK$COLOR_BACKGROUND$ --color SHADEA$COLOR_BACKGROUND$ --color SHADEB$COLOR_BACKGROUND$ --color CANVAS$COLOR_CANVAS$  --color FONT$COLOR_FONT$ --color AXIS$COLOR_AXIS$ --color ARROW$COLOR_ARROW$ DEF:idle=cpu/percent-idle.rrd:value:AVERAGE DEF:idle_min=cpu/percent-idle.rrd:value:MIN DEF:idle_max=cpu/percent-idle.rrd:value:MAX CDEF:idle_max_min_delta=idle_max,idle_min,- LINE:idle_min AREA:idle_max_min_delta$COLOR_LINE_SINGLE_SUB$::STACK LINE$LINE_WIDTH_PRIMARY$:idle$COLOR_LINE_SINGLE$:\"idle\\l\" COMMENT:\\u GPRINT:idle:AVERAGE:\"Avr %1.0lf\" GPRINT:idle_min:MIN:\"Min %1.0lf\" GPRINT:idle_max:MAX:\"Max %1.0lf\" GPRINT:idle:LAST:\"Last %1.0lf\\r\"  "
      }, 
      "CPU/wait": {
         "files": [
            "cpu/percent-wait.rrd"
         ], 
         "command": "-t \"CPU wait, %\" --upper-limit 100 --lower-limit 0 --rigid --color BACK$COLOR_BACKGROUND$ --color SHADEA$COLOR_BACKGROUND$ --color SHADEB$COLOR_BACKGROUND$ --color CANVAS$COLOR_CANVAS$  --color FONT$COLOR_FONT$ --color AXIS$COLOR_AXIS$ --color ARROW$COLOR_ARROW$ DEF:wait=cpu/percent-wait.rrd:value:AVERAGE DEF:wait_min=cpu/percent-wait.rrd:value:MIN DEF:wait_max=cpu/percent-wait.rrd:value:MAX CDEF:wait_max_min_delta=wait_max,wait_min,- LINE:wait_min AREA:wait_max_min_delta$COLOR_LINE_SINGLE_SUB$::STACK LINE$LINE_WIDTH_PRIMARY$:wait$COLOR_LINE_SINGLE$:\"wait\\l\" COMMENT:\\u GPRINT:wait:AVERAGE:\"Avr %1.0lf\" GPRINT:wait_min:MIN:\"Min %1.0lf\" GPRINT:wait_max:MAX:\"Max %1.0lf\" GPRINT:wait:LAST:\"Last %1.0lf\\r\"  "
      }, 
      "Entropy/entropy": {
         "files": [
            "entropy/entropy.rrd"
         ], 
         "command": "-t \" Entropy, bits\"   --color BACK$COLOR_BACKGROUND$ --color SHADEA$COLOR_BACKGROUND$ --color SHADEB$COLOR_BACKGROUND$ --color CANVAS$COLOR_CANVAS$  --color FONT$COLOR_FONT$ --color AXIS$COLOR_AXIS$ --color ARROW$COLOR_ARROW$ DEF:entropy=entropy/entropy.rrd:value:AVERAGE DEF:entropy_min=entropy/entropy.rrd:value:MIN DEF:entropy_max=entropy/entropy.rrd:value:MAX CDEF:entropy_max_min_delta=entropy_max,entropy_min,- LINE:entropy_min AREA:entropy_max_min_delta$COLOR_LINE_SINGLE_SUB$::STACK LINE$LINE_WIDTH_PRIMARY$:entropy$COLOR_LINE_SINGLE$:\" \\l\" COMMENT:\\u GPRINT:entropy:AVERAGE:\"Avr %1.0lf%S\" GPRINT:entropy_min:MIN:\"Min %1.0lf%S\" GPRINT:entropy_max:MAX:\"Max %1.0lf%S\" GPRINT:entropy:LAST:\"Last %1.0lf%S\\r\"  "
      }, 
      "CPU/steal": {
         "files": [
            "cpu/percent-steal.rrd"
         ], 
         "command": "-t \"CPU steal, %\" --upper-limit 100 --lower-limit 0 --rigid --color BACK$COLOR_BACKGROUND$ --color SHADEA$COLOR_BACKGROUND$ --color SHADEB$COLOR_BACKGROUND$ --color CANVAS$COLOR_CANVAS$  --color FONT$COLOR_FONT$ --color AXIS$COLOR_AXIS$ --color ARROW$COLOR_ARROW$ DEF:steal=cpu/percent-steal.rrd:value:AVERAGE DEF:steal_min=cpu/percent-steal.rrd:value:MIN DEF:steal_max=cpu/percent-steal.rrd:value:MAX CDEF:steal_max_min_delta=steal_max,steal_min,- LINE:steal_min AREA:steal_max_min_delta$COLOR_LINE_SINGLE_SUB$::STACK LINE$LINE_WIDTH_PRIMARY$:steal$COLOR_LINE_SINGLE$:\"steal\\l\" COMMENT:\\u GPRINT:steal:AVERAGE:\"Avr %1.0lf\" GPRINT:steal_min:MIN:\"Min %1.0lf\" GPRINT:steal_max:MAX:\"Max %1.0lf\" GPRINT:steal:LAST:\"Last %1.0lf\\r\"  "
      }, 
      "Context/context_switch": {
         "files": [
            "contextswitch/contextswitch.rrd"
         ], 
         "command": "-t \" Context switch, 1/s\"   --color BACK$COLOR_BACKGROUND$ --color SHADEA$COLOR_BACKGROUND$ --color SHADEB$COLOR_BACKGROUND$ --color CANVAS$COLOR_CANVAS$  --color FONT$COLOR_FONT$ --color AXIS$COLOR_AXIS$ --color ARROW$COLOR_ARROW$ DEF:context_switch=contextswitch/contextswitch.rrd:value:AVERAGE DEF:context_switch_min=contextswitch/contextswitch.rrd:value:MIN DEF:context_switch_max=contextswitch/contextswitch.rrd:value:MAX CDEF:context_switch_max_min_delta=context_switch_max,context_switch_min,- LINE:context_switch_min AREA:context_switch_max_min_delta$COLOR_LINE_SINGLE_SUB$::STACK LINE$LINE_WIDTH_PRIMARY$:context_switch$COLOR_LINE_SINGLE$:\" \\l\" COMMENT:\\u GPRINT:context_switch:AVERAGE:\"Avr %1.0lf%S\" GPRINT:context_switch_min:MIN:\"Min %1.0lf%S\" GPRINT:context_switch_max:MAX:\"Max %1.0lf%S\" GPRINT:context_switch:LAST:\"Last %1.0lf%S\\r\"  "
      }, 
      "CPU/interrupt": {
         "files": [
            "cpu/percent-interrupt.rrd"
         ], 
         "command": "-t \"CPU interrupt, %\" --upper-limit 100 --lower-limit 0 --rigid --color BACK$COLOR_BACKGROUND$ --color SHADEA$COLOR_BACKGROUND$ --color SHADEB$COLOR_BACKGROUND$ --color CANVAS$COLOR_CANVAS$  --color FONT$COLOR_FONT$ --color AXIS$COLOR_AXIS$ --color ARROW$COLOR_ARROW$ DEF:interrupt=cpu/percent-interrupt.rrd:value:AVERAGE DEF:interrupt_min=cpu/percent-interrupt.rrd:value:MIN DEF:interrupt_max=cpu/percent-interrupt.rrd:value:MAX CDEF:interrupt_max_min_delta=interrupt_max,interrupt_min,- LINE:interrupt_min AREA:interrupt_max_min_delta$COLOR_LINE_SINGLE_SUB$::STACK LINE$LINE_WIDTH_PRIMARY$:interrupt$COLOR_LINE_SINGLE$:\"interrupt\\l\" COMMENT:\\u GPRINT:interrupt:AVERAGE:\"Avr %1.0lf\" GPRINT:interrupt_min:MIN:\"Min %1.0lf\" GPRINT:interrupt_max:MAX:\"Max %1.0lf\" GPRINT:interrupt:LAST:\"Last %1.0lf\\r\"  "
      }, 
      "Memory/free": {
         "files": [
            "memory/memory-free.rrd"
         ], 
         "command": "-t \" Memory free, bytes\"   --color BACK$COLOR_BACKGROUND$ --color SHADEA$COLOR_BACKGROUND$ --color SHADEB$COLOR_BACKGROUND$ --color CANVAS$COLOR_CANVAS$  --color FONT$COLOR_FONT$ --color AXIS$COLOR_AXIS$ --color ARROW$COLOR_ARROW$ DEF:free=memory/memory-free.rrd:value:AVERAGE DEF:free_min=memory/memory-free.rrd:value:MIN DEF:free_max=memory/memory-free.rrd:value:MAX CDEF:free_max_min_delta=free_max,free_min,- LINE:free_min AREA:free_max_min_delta$COLOR_LINE_SINGLE_SUB$::STACK LINE$LINE_WIDTH_PRIMARY$:free$COLOR_LINE_SINGLE$:\" \\l\" COMMENT:\\u GPRINT:free:AVERAGE:\"Avr %4.0lf%S\" GPRINT:free_min:MIN:\"Min %4.0lf%S\" GPRINT:free_max:MAX:\"Max %4.0lf%S\" GPRINT:free:LAST:\"Last %4.0lf%S\\r\"  "
      }, 
      "Memory/cached": {
         "files": [
            "memory/memory-cached.rrd"
         ], 
         "command": "-t \" Memory cached, bytes\"   --color BACK$COLOR_BACKGROUND$ --color SHADEA$COLOR_BACKGROUND$ --color SHADEB$COLOR_BACKGROUND$ --color CANVAS$COLOR_CANVAS$  --color FONT$COLOR_FONT$ --color AXIS$COLOR_AXIS$ --color ARROW$COLOR_ARROW$ DEF:cached=memory/memory-cached.rrd:value:AVERAGE DEF:cached_min=memory/memory-cached.rrd:value:MIN DEF:cached_max=memory/memory-cached.rrd:value:MAX CDEF:cached_max_min_delta=cached_max,cached_min,- LINE:cached_min AREA:cached_max_min_delta$COLOR_LINE_SINGLE_SUB$::STACK LINE$LINE_WIDTH_PRIMARY$:cached$COLOR_LINE_SINGLE$:\" \\l\" COMMENT:\\u GPRINT:cached:AVERAGE:\"Avr %4.0lf%S\" GPRINT:cached_min:MIN:\"Min %4.0lf%S\" GPRINT:cached_max:MAX:\"Max %4.0lf%S\" GPRINT:cached:LAST:\"Last %4.0lf%S\\r\"  "
      }, 
      "Memory/buffered": {
         "files": [
            "memory/memory-buffered.rrd"
         ], 
         "command": "-t \" Memory buffered, bytes\"   --color BACK$COLOR_BACKGROUND$ --color SHADEA$COLOR_BACKGROUND$ --color SHADEB$COLOR_BACKGROUND$ --color CANVAS$COLOR_CANVAS$  --color FONT$COLOR_FONT$ --color AXIS$COLOR_AXIS$ --color ARROW$COLOR_ARROW$ DEF:buffered=memory/memory-buffered.rrd:value:AVERAGE DEF:buffered_min=memory/memory-buffered.rrd:value:MIN DEF:buffered_max=memory/memory-buffered.rrd:value:MAX CDEF:buffered_max_min_delta=buffered_max,buffered_min,- LINE:buffered_min AREA:buffered_max_min_delta$COLOR_LINE_SINGLE_SUB$::STACK LINE$LINE_WIDTH_PRIMARY$:buffered$COLOR_LINE_SINGLE$:\" \\l\" COMMENT:\\u GPRINT:buffered:AVERAGE:\"Avr %4.0lf%S\" GPRINT:buffered_min:MIN:\"Min %4.0lf%S\" GPRINT:buffered_max:MAX:\"Max %4.0lf%S\" GPRINT:buffered:LAST:\"Last %4.0lf%S\\r\"  "
      }, 
      "CPU/user": {
         "files": [
            "cpu/percent-user.rrd"
         ], 
         "command": "-t \"CPU user, %\" --upper-limit 100 --lower-limit 0 --rigid --color BACK$COLOR_BACKGROUND$ --color SHADEA$COLOR_BACKGROUND$ --color SHADEB$COLOR_BACKGROUND$ --color CANVAS$COLOR_CANVAS$  --color FONT$COLOR_FONT$ --color AXIS$COLOR_AXIS$ --color ARROW$COLOR_ARROW$ DEF:user=cpu/percent-user.rrd:value:AVERAGE DEF:user_min=cpu/percent-user.rrd:value:MIN DEF:user_max=cpu/percent-user.rrd:value:MAX CDEF:user_max_min_delta=user_max,user_min,- LINE:user_min AREA:user_max_min_delta$COLOR_LINE_SINGLE_SUB$::STACK LINE$LINE_WIDTH_PRIMARY$:user$COLOR_LINE_SINGLE$:\"user\\l\" COMMENT:\\u GPRINT:user:AVERAGE:\"Avr %1.0lf\" GPRINT:user_min:MIN:\"Min %1.0lf\" GPRINT:user_max:MAX:\"Max %1.0lf\" GPRINT:user:LAST:\"Last %1.0lf\\r\"  "
      }, 
      "CPU/softirq": {
         "files": [
            "cpu/percent-softirq.rrd"
         ], 
         "command": "-t \"CPU softirq, %\" --upper-limit 100 --lower-limit 0 --rigid --color BACK$COLOR_BACKGROUND$ --color SHADEA$COLOR_BACKGROUND$ --color SHADEB$COLOR_BACKGROUND$ --color CANVAS$COLOR_CANVAS$  --color FONT$COLOR_FONT$ --color AXIS$COLOR_AXIS$ --color ARROW$COLOR_ARROW$ DEF:softirq=cpu/percent-softirq.rrd:value:AVERAGE DEF:softirq_min=cpu/percent-softirq.rrd:value:MIN DEF:softirq_max=cpu/percent-softirq.rrd:value:MAX CDEF:softirq_max_min_delta=softirq_max,softirq_min,- LINE:softirq_min AREA:softirq_max_min_delta$COLOR_LINE_SINGLE_SUB$::STACK LINE$LINE_WIDTH_PRIMARY$:softirq$COLOR_LINE_SINGLE$:\"softirq\\l\" COMMENT:\\u GPRINT:softirq:AVERAGE:\"Avr %1.0lf\" GPRINT:softirq_min:MIN:\"Min %1.0lf\" GPRINT:softirq_max:MAX:\"Max %1.0lf\" GPRINT:softirq:LAST:\"Last %1.0lf\\r\"  "
      }, 
      "Uptime/uptime": {
         "files": [
            "uptime/uptime.rrd"
         ], 
         "command": "-t \"Uptime, days\" --color BACK$COLOR_BACKGROUND$ --color SHADEA$COLOR_BACKGROUND$ --color SHADEB$COLOR_BACKGROUND$ --color CANVAS$COLOR_CANVAS$  --color FONT$COLOR_FONT$ --color AXIS$COLOR_AXIS$ --color ARROW$COLOR_ARROW$ DEF:uptime_data=uptime/uptime.rrd:value:AVERAGE CDEF:uptime=uptime_data,86400,/ LINE$LINE_WIDTH_PRIMARY$:uptime$COLOR_LINE_SINGLE$:\"uptime\\l\" COMMENT:\\u GPRINT:uptime:LAST:\"Current %0.2lf\\r\"  "
      }, 
      "Storage/root": {
         "files": [
            "df-root/df_complex-used.rrd", 
            "df-root/df_complex-reserved.rrd", 
            "df-root/df_complex-free.rrd"
         ], 
         "command": "-t \"Storage root\" --lower-limit 0 --color BACK$COLOR_BACKGROUND$ --color SHADEA$COLOR_BACKGROUND$ --color SHADEB$COLOR_BACKGROUND$ --color CANVAS$COLOR_CANVAS$  --color FONT$COLOR_FONT$ --color AXIS$COLOR_AXIS$ --color ARROW$COLOR_ARROW$ DEF:used=df-root/df_complex-used.rrd:value:AVERAGE DEF:reserved=df-root/df_complex-reserved.rrd:value:AVERAGE DEF:free=df-root/df_complex-free.rrd:value:AVERAGE AREA:used#E41A1CFF:\"used\\l\" COMMENT:\\u GPRINT:used:AVERAGE:\"Avr %2.0lf%S\" GPRINT:used:MIN:\"Min %2.0lf%S\" GPRINT:used:MAX:\"Max %2.0lf%S\" GPRINT:used:LAST:\"Last %2.0lf%S\\r\"  AREA:reserved#377EB8FF:\"reserved\\l\":STACK COMMENT:\\u GPRINT:reserved:AVERAGE:\"Avr %2.0lf%S\" GPRINT:reserved:MIN:\"Min %2.0lf%S\" GPRINT:reserved:MAX:\"Max %2.0lf%S\" GPRINT:reserved:LAST:\"Last %2.0lf%S\\r\"  AREA:free#4DAF4AFF:\"free\\l\":STACK COMMENT:\\u GPRINT:free:AVERAGE:\"Avr %2.0lf%S\" GPRINT:free:MIN:\"Min %2.0lf%S\" GPRINT:free:MAX:\"Max %2.0lf%S\" GPRINT:free:LAST:\"Last %2.0lf%S\\r\"  "
      }, 
      "Load/load": {
         "files": [
            "load/load.rrd"
         ], 
         "command": "-t \"Load\" --lower-limit 0 --color BACK$COLOR_BACKGROUND$ --color SHADEA$COLOR_BACKGROUND$ --color SHADEB$COLOR_BACKGROUND$ --color CANVAS$COLOR_CANVAS$  --color FONT$COLOR_FONT$ --color AXIS$COLOR_AXIS$ --color ARROW$COLOR_ARROW$ DEF:shortterm=load/load.rrd:shortterm:AVERAGE DEF:shortterm_min=load/load.rrd:shortterm:MIN DEF:shortterm_max=load/load.rrd:shortterm:MAX CDEF:shortterm_max_min_delta=shortterm_max,shortterm_min,- LINE:shortterm_min AREA:shortterm_max_min_delta#E41A1C80::STACK DEF:midterm=load/load.rrd:midterm:AVERAGE DEF:midterm_min=load/load.rrd:midterm:MIN DEF:midterm_max=load/load.rrd:midterm:MAX CDEF:midterm_max_min_delta=midterm_max,midterm_min,- LINE:midterm_min AREA:midterm_max_min_delta#377EB880::STACK DEF:longterm=load/load.rrd:longterm:AVERAGE DEF:longterm_min=load/load.rrd:longterm:MIN DEF:longterm_max=load/load.rrd:longterm:MAX CDEF:longterm_max_min_delta=longterm_max,longterm_min,- LINE:longterm_min AREA:longterm_max_min_delta#4DAF4A80::STACK LINE$LINE_WIDTH_PRIMARY$:shortterm#E41A1CFF:\"shortterm\\l\" COMMENT:\\u GPRINT:shortterm:AVERAGE:\"Avr %0.2lf\" GPRINT:shortterm_min:MIN:\"Min %0.2lf\" GPRINT:shortterm_max:MAX:\"Max %0.2lf\" GPRINT:shortterm:LAST:\"Last %0.2lf\\r\"  LINE$LINE_WIDTH_PRIMARY$:midterm#377EB8FF:\"midterm\\l\" COMMENT:\\u GPRINT:midterm:AVERAGE:\"Avr %0.2lf\" GPRINT:midterm_min:MIN:\"Min %0.2lf\" GPRINT:midterm_max:MAX:\"Max %0.2lf\" GPRINT:midterm:LAST:\"Last %0.2lf\\r\"  LINE$LINE_WIDTH_PRIMARY$:longterm#4DAF4AFF:\"longterm\\l\" COMMENT:\\u GPRINT:longterm:AVERAGE:\"Avr %0.2lf\" GPRINT:longterm_min:MIN:\"Min %0.2lf\" GPRINT:longterm_max:MAX:\"Max %0.2lf\" GPRINT:longterm:LAST:\"Last %0.2lf\\r\"  "
      }, 
      "Memory/used": {
         "files": [
            "memory/memory-used.rrd"
         ], 
         "command": "-t \" Memory used, bytes\"   --color BACK$COLOR_BACKGROUND$ --color SHADEA$COLOR_BACKGROUND$ --color SHADEB$COLOR_BACKGROUND$ --color CANVAS$COLOR_CANVAS$  --color FONT$COLOR_FONT$ --color AXIS$COLOR_AXIS$ --color ARROW$COLOR_ARROW$ DEF:used=memory/memory-used.rrd:value:AVERAGE DEF:used_min=memory/memory-used.rrd:value:MIN DEF:used_max=memory/memory-used.rrd:value:MAX CDEF:used_max_min_delta=used_max,used_min,- LINE:used_min AREA:used_max_min_delta$COLOR_LINE_SINGLE_SUB$::STACK LINE$LINE_WIDTH_PRIMARY$:used$COLOR_LINE_SINGLE$:\" \\l\" COMMENT:\\u GPRINT:used:AVERAGE:\"Avr %4.0lf%S\" GPRINT:used_min:MIN:\"Min %4.0lf%S\" GPRINT:used_max:MAX:\"Max %4.0lf%S\" GPRINT:used:LAST:\"Last %4.0lf%S\\r\"  "
      }, 
      "Memory/slab_recl": {
         "files": [
            "memory/memory-slab_recl.rrd"
         ], 
         "command": "-t \" Memory slab_recl, bytes\"   --color BACK$COLOR_BACKGROUND$ --color SHADEA$COLOR_BACKGROUND$ --color SHADEB$COLOR_BACKGROUND$ --color CANVAS$COLOR_CANVAS$  --color FONT$COLOR_FONT$ --color AXIS$COLOR_AXIS$ --color ARROW$COLOR_ARROW$ DEF:slab_recl=memory/memory-slab_recl.rrd:value:AVERAGE DEF:slab_recl_min=memory/memory-slab_recl.rrd:value:MIN DEF:slab_recl_max=memory/memory-slab_recl.rrd:value:MAX CDEF:slab_recl_max_min_delta=slab_recl_max,slab_recl_min,- LINE:slab_recl_min AREA:slab_recl_max_min_delta$COLOR_LINE_SINGLE_SUB$::STACK LINE$LINE_WIDTH_PRIMARY$:slab_recl$COLOR_LINE_SINGLE$:\" \\l\" COMMENT:\\u GPRINT:slab_recl:AVERAGE:\"Avr %4.0lf%S\" GPRINT:slab_recl_min:MIN:\"Min %4.0lf%S\" GPRINT:slab_recl_max:MAX:\"Max %4.0lf%S\" GPRINT:slab_recl:LAST:\"Last %4.0lf%S\\r\"  "
      }, 
      "Battery/current": {
         "files": [
            "battery-0/current.rrd"
         ], 
         "command": "-t \" Battery current, A\"   --color BACK$COLOR_BACKGROUND$ --color SHADEA$COLOR_BACKGROUND$ --color SHADEB$COLOR_BACKGROUND$ --color CANVAS$COLOR_CANVAS$  --color FONT$COLOR_FONT$ --color AXIS$COLOR_AXIS$ --color ARROW$COLOR_ARROW$ DEF:current=battery-0/current.rrd:value:AVERAGE DEF:current_min=battery-0/current.rrd:value:MIN DEF:current_max=battery-0/current.rrd:value:MAX CDEF:current_max_min_delta=current_max,current_min,- LINE:current_min AREA:current_max_min_delta$COLOR_LINE_SINGLE_SUB$::STACK LINE$LINE_WIDTH_PRIMARY$:current$COLOR_LINE_SINGLE$:\" \\l\" COMMENT:\\u GPRINT:current:AVERAGE:\"Avr %1.0lf%S\" GPRINT:current_min:MIN:\"Min %1.0lf%S\" GPRINT:current_max:MAX:\"Max %1.0lf%S\" GPRINT:current:LAST:\"Last %1.0lf%S\\r\"  "
      }, 
      "Memory/overview": {
         "files": [
            "memory/memory-slab_unrecl.rrd", 
            "memory/memory-slab_recl.rrd", 
            "memory/memory-used.rrd", 
            "memory/memory-buffered.rrd", 
            "memory/memory-cached.rrd", 
            "memory/memory-free.rrd"
         ], 
         "command": "-t \"Memory overview, bytes\" --lower-limit 0 --color BACK$COLOR_BACKGROUND$ --color SHADEA$COLOR_BACKGROUND$ --color SHADEB$COLOR_BACKGROUND$ --color CANVAS$COLOR_CANVAS$  --color FONT$COLOR_FONT$ --color AXIS$COLOR_AXIS$ --color ARROW$COLOR_ARROW$ DEF:slab_unrecl=memory/memory-slab_unrecl.rrd:value:AVERAGE DEF:slab_recl=memory/memory-slab_recl.rrd:value:AVERAGE DEF:used=memory/memory-used.rrd:value:AVERAGE DEF:buffered=memory/memory-buffered.rrd:value:AVERAGE DEF:cached=memory/memory-cached.rrd:value:AVERAGE DEF:free=memory/memory-free.rrd:value:AVERAGE AREA:slab_unrecl#E41A1CFF:\"slab_unrecl\\l\" COMMENT:\\u GPRINT:slab_unrecl:AVERAGE:\"Avr %4.0lf%S\" GPRINT:slab_unrecl:MIN:\"Min %4.0lf%S\" GPRINT:slab_unrecl:MAX:\"Max %4.0lf%S\" GPRINT:slab_unrecl:LAST:\"Last %4.0lf%S\\r\"  AREA:slab_recl#377EB8FF:\"slab_recl\\l\":STACK COMMENT:\\u GPRINT:slab_recl:AVERAGE:\"Avr %4.0lf%S\" GPRINT:slab_recl:MIN:\"Min %4.0lf%S\" GPRINT:slab_recl:MAX:\"Max %4.0lf%S\" GPRINT:slab_recl:LAST:\"Last %4.0lf%S\\r\"  AREA:used#4DAF4AFF:\"used\\l\":STACK COMMENT:\\u GPRINT:used:AVERAGE:\"Avr %4.0lf%S\" GPRINT:used:MIN:\"Min %4.0lf%S\" GPRINT:used:MAX:\"Max %4.0lf%S\" GPRINT:used:LAST:\"Last %4.0lf%S\\r\"  AREA:buffered#984EA3FF:\"buffered\\l\":STACK COMMENT:\\u GPRINT:buffered:AVERAGE:\"Avr %4.0lf%S\" GPRINT:buffered:MIN:\"Min %4.0lf%S\" GPRINT:buffered:MAX:\"Max %4.0lf%S\" GPRINT:buffered:LAST:\"Last %4.0lf%S\\r\"  AREA:cached#FF7F00FF:\"cached\\l\":STACK COMMENT:\\u GPRINT:cached:AVERAGE:\"Avr %4.0lf%S\" GPRINT:cached:MIN:\"Min %4.0lf%S\" GPRINT:cached:MAX:\"Max %4.0lf%S\" GPRINT:cached:LAST:\"Last %4.0lf%S\\r\"  AREA:free#FFFF33FF:\"free\\l\":STACK COMMENT:\\u GPRINT:free:AVERAGE:\"Avr %4.0lf%S\" GPRINT:free:MIN:\"Min %4.0lf%S\" GPRINT:free:MAX:\"Max %4.0lf%S\" GPRINT:free:LAST:\"Last %4.0lf%S\\r\"  "
      }, 
      "Memory/slab_unrecl": {
         "files": [
            "memory/memory-slab_unrecl.rrd"
         ], 
         "command": "-t \" Memory slab_unrecl, bytes\"   --color BACK$COLOR_BACKGROUND$ --color SHADEA$COLOR_BACKGROUND$ --color SHADEB$COLOR_BACKGROUND$ --color CANVAS$COLOR_CANVAS$  --color FONT$COLOR_FONT$ --color AXIS$COLOR_AXIS$ --color ARROW$COLOR_ARROW$ DEF:slab_unrecl=memory/memory-slab_unrecl.rrd:value:AVERAGE DEF:slab_unrecl_min=memory/memory-slab_unrecl.rrd:value:MIN DEF:slab_unrecl_max=memory/memory-slab_unrecl.rrd:value:MAX CDEF:slab_unrecl_max_min_delta=slab_unrecl_max,slab_unrecl_min,- LINE:slab_unrecl_min AREA:slab_unrecl_max_min_delta$COLOR_LINE_SINGLE_SUB$::STACK LINE$LINE_WIDTH_PRIMARY$:slab_unrecl$COLOR_LINE_SINGLE$:\" \\l\" COMMENT:\\u GPRINT:slab_unrecl:AVERAGE:\"Avr %4.0lf%S\" GPRINT:slab_unrecl_min:MIN:\"Min %4.0lf%S\" GPRINT:slab_unrecl_max:MAX:\"Max %4.0lf%S\" GPRINT:slab_unrecl:LAST:\"Last %4.0lf%S\\r\"  "
      }, 
      "Battery/voltage": {
         "files": [
            "battery-0/voltage.rrd"
         ], 
         "command": "-t \" Battery voltage, V\"   --color BACK$COLOR_BACKGROUND$ --color SHADEA$COLOR_BACKGROUND$ --color SHADEB$COLOR_BACKGROUND$ --color CANVAS$COLOR_CANVAS$  --color FONT$COLOR_FONT$ --color AXIS$COLOR_AXIS$ --color ARROW$COLOR_ARROW$ DEF:voltage=battery-0/voltage.rrd:value:AVERAGE DEF:voltage_min=battery-0/voltage.rrd:value:MIN DEF:voltage_max=battery-0/voltage.rrd:value:MAX CDEF:voltage_max_min_delta=voltage_max,voltage_min,- LINE:voltage_min AREA:voltage_max_min_delta$COLOR_LINE_SINGLE_SUB$::STACK LINE$LINE_WIDTH_PRIMARY$:voltage$COLOR_LINE_SINGLE$:\" \\l\" COMMENT:\\u GPRINT:voltage:AVERAGE:\"Avr %1.3lf%S\" GPRINT:voltage_min:MIN:\"Min %1.3lf%S\" GPRINT:voltage_max:MAX:\"Max %1.3lf%S\" GPRINT:voltage:LAST:\"Last %1.3lf%S\\r\"  "
      }
   }
}
